Ex6/decoder_4_to_16/dec4_16.v
module dec4_16 (a,b,c,d,o);

input a,b,c,d;

output [15:0] o;

wire a0 , b0 , c0 , d0;

not (a0,a);
not (b0,b);
not (c0,c);
not (d0,d);

and (o[0], d0,a0,b0,c0);
and (o[1], d0,a0,b0,c);
and (o[2], d0,a0,b,c0);
and (o[3], d0,a0,b,c);

and (o[4], d0,a,b0,c0);
and (o[5], d0,a,b0,c);
and (o[6], d0,a,b,c0);
and (o[7], d0,a,b,c);

and (o[8],  d,a0,b0,c);
and (o[9],  d,a0,b0,c);
and (o[10], d,a0,b0,c);
and (o[11], d,a0,b0,c);

and (o[12], d,a0,b0,c);
and (o[13], d,a0,b0,c);
and (o[14], d,a0,b0,c);
and (o[15], d,a0,b0,c);

endmodule

Ex6/decoder_4_to_16/dec4_16_tb.v
`timescale 1ns/1ns
`include "dec4_16.v"

module dec4_16_tb;

reg a,b,c,d;
output [15:0] o;

dec4_16 uut(a,b,c,d,o);

initial begin
    
    $dumpfile("dec4_16_tb.vcd");
    $dumpvars(0 , dec4_16_tb);

    a = 0; b = 0; c = 0; d = 0; #10;
    a = 0; b = 0; c = 0; d = 1; #10;
    a = 0; b = 0; c = 1; d = 0; #10;
    a = 0; b = 0; c = 1; d = 1; #10;
    a = 0; b = 1; c = 0; d = 0; #10;
    a = 0; b = 1; c = 0; d = 1; #10;
    a = 0; b = 1; c = 1; d = 0; #10;
    a = 0; b = 1; c = 1; d = 1; #10;
    a = 1; b = 0; c = 0; d = 0; #10;
    a = 1; b = 0; c = 0; d = 1; #10;
    a = 1; b = 0; c = 1; d = 0; #10;
    a = 1; b = 0; c = 1; d = 1; #10;
    a = 1; b = 1; c = 0; d = 0; #10;
    a = 1; b = 1; c = 0; d = 1; #10;
    a = 1; b = 1; c = 1; d = 0; #10;
    a = 1; b = 1; c = 1; d = 1; #10;


    $display("complete!!!");

end

endmodule

Ex6/decoder_4_to_16/dec4_16_tb.vcd
$date
	Tue Nov 16 13:43:12 2021
$end
$version
	Icarus Verilog
$end
$timescale
	1ns
$end
$scope module dec4_16_tb $end
$var wire 16 ! o [15:0] $end
$var reg 1 " a $end
$var reg 1 # b $end
$var reg 1 $ c $end
$var reg 1 % d $end
$scope module uut $end
$var wire 1 " a $end
$var wire 1 & a0 $end
$var wire 1 # b $end
$var wire 1 ' b0 $end
$var wire 1 $ c $end
$var wire 1 ( c0 $end
$var wire 1 % d $end
$var wire 1 ) d0 $end
$var wire 16 * o [15:0] $end
$upscope $end
$upscope $end
$enddefinitions $end
#0
$dumpvars
b1 *
1)
1(
1'
1&
0%
0$
0#
0"
b1 !
$end
#10
b0 !
b0 *
0)
1%
#20
b10 !
b10 *
1)
0(
0%
1$
#30
0)
b1111111100000000 !
b1111111100000000 *
1%
#40
1)
1(
b100 !
b100 *
0'
0%
0$
1#
#50
b0 !
b0 *
0)
1%
#60
b1000 !
b1000 *
1)
0(
0%
1$
#70
b0 !
b0 *
0)
1%
#80
b10000 !
b10000 *
1)
1(
1'
0&
0%
0$
0#
1"
#90
b0 !
b0 *
0)
1%
#100
b100000 !
b100000 *
1)
0(
0%
1$
#110
b0 !
b0 *
0)
1%
#120
b1000000 !
b1000000 *
1)
1(
0'
0%
0$
1#
#130
b0 !
b0 *
0)
1%
#140
b10000000 !
b10000000 *
1)
0(
0%
1$
#150
b0 !
b0 *
0)
1%
